CHANGES.md
MANIFEST.in
README.md
setup.py
pytunnel/__init__.py
pytunnel/__init__.pyc
pytunnel/__main__.py
pytunnel/tunnel.py
pytunnel/tunnel.pyc
pytunnel.egg-info/PKG-INFO
pytunnel.egg-info/SOURCES.txt
pytunnel.egg-info/dependency_links.txt
pytunnel.egg-info/not-zip-safe
pytunnel.egg-info/top_level.txt
pytunnel/__pycache__/__init__.cpython-311.pyc
pytunnel/__pycache__/__init__.cpython-37.pyc
pytunnel/__pycache__/__init__.cpython-39.pyc
pytunnel/__pycache__/__main__.cpython-311.pyc
pytunnel/__pycache__/__main__.cpython-37.pyc
pytunnel/__pycache__/__main__.cpython-39.pyc
pytunnel/__pycache__/tunnel.cpython-311.pyc
pytunnel/__pycache__/tunnel.cpython-37.pyc
pytunnel/__pycache__/tunnel.cpython-39.pyc