Metadata-Version: 2.1
Name: pytunnel
Version: 2.4.2
Summary: A TCP tunnel server/client by Python.
Home-page: https://github.com/sintrb/pytunnel/
Author: trb
Author-email: sintrb@gmail.com
License: UNKNOWN
Keywords: pytunnel,tunnel,proxy,socket
Platform: UNKNOWN
